oltea_dummy_pack/__init__.py
oltea_dummy_pack/__main__.py
oltea_dummy_pack/mama.py
oltea_dummy_pack/rares.py
oltea_dummy_pack-1.2.0.dist-info/LICENSE
oltea_dummy_pack-1.2.0.dist-info/METADATA
oltea_dummy_pack-1.2.0.dist-info/WHEEL
oltea_dummy_pack-1.2.0.dist-info/top_level.txt
oltea_dummy_pack-1.2.0.dist-info/RECORD
