Metadata-Version: 2.1
Name: oltea-dummy-pack
Version: 1.2.0
Summary: Dummy pack for testing
License-File: LICENSE
